test/__init__.py
test/test_extractor.py
test/test_pdf.py
test/test_utils.py
test/common/__init__.py
test/common/utils_4_tests.py
test/cv/__init__.py
test/cv/test_data.py
test/deploy/__init__.py
test/deploy/test_app.py
test/imports/__init__.py
test/imports/test_imports.py
test/nlp/__init__.py
test/nlp/test_data.py
test/tabular/__init__.py
test/tabular/test_data.py
test/test_common/__init__.py
test/test_common/utils_4_tests.py
tools/__init__.py
tools/clean_docs.py
tools/nbdev_tools.py
tools/test_extractor.py
unpackai/__init__.py
unpackai/_nbdev.py
unpackai/bug.py
unpackai/deploy.py
unpackai/pdf.py
unpackai/utils.py
unpackai/cv/__init__.py
unpackai/cv/data.py
unpackai/deploy/__init__.py
unpackai/deploy/app.py
unpackai/deploy/cv.py
unpackai/interp/__init__.py
unpackai/interp/latent.py
unpackai/interp/vision.py
unpackai/nlp/__init__.py
unpackai/nlp/data.py
unpackai/nlp/interp.py
unpackai/static/html/download_button.html
unpackai/static/html/bug/error_report.html
unpackai/static/html/bug/error_tiny_page.html
unpackai/tabular/__init__.py
unpackai/tabular/data.py
unpackai/turk/__init__.py
unpackai/turk/image.py
unpackai-0.1.9.6.dist-info/LICENSE
unpackai-0.1.9.6.dist-info/METADATA
unpackai-0.1.9.6.dist-info/WHEEL
unpackai-0.1.9.6.dist-info/entry_points.txt
unpackai-0.1.9.6.dist-info/top_level.txt
unpackai-0.1.9.6.dist-info/RECORD
