Metadata-Version: 2.1
Name: unpackai
Version: 0.1.9.6
Summary: UnpackAI, the library
Home-page: https://github.com/unpackai/unpackai
Author: Xiaochen (Ray) Zhang
Author-email: b2ray2c@gmail.com
License: MIT
Project-URL: Documentation, https://unpackai.github.io/unpackai/
Project-URL: Tracker, https://github.com/unpackAI/unpackai/issues
Keywords: python fastai data science pytorch
Platform: UNKNOWN
Classifier: Development Status :: 3 - Alpha
Classifier: Intended Audience :: Developers
Classifier: License :: OSI Approved :: MIT License
Classifier: Natural Language :: English
Classifier: Programming Language :: Python :: 3.6
Classifier: Programming Language :: Python :: 3.7
Classifier: Programming Language :: Python :: 3.8
Requires-Python: >=3.6
Requires-Dist: fastai (>=2.5)
Requires-Dist: forgebox (>=0.4.5)
Requires-Dist: beautifulsoup4
Requires-Dist: graphviz
Provides-Extra: pdf
Requires-Dist: pdfminer.six ; extra == 'pdf'
Provides-Extra: deploy
Requires-Dist: streamlit ; extra == 'deploy'
Requires-Dist: pyngrok ; extra == 'deploy'
Requires-Dist: jinja2 ; extra == 'deploy'
Requires-Dist: black ; extra == 'deploy'
